xmldt/__init__.py
xmldt/element.py
xmldt/htmldt.py
xmldt/reindent.py
xmldt/skel.py
xmldt-0.0.13.dist-info/entry_points.txt
xmldt-0.0.13.dist-info/LICENSE
xmldt-0.0.13.dist-info/WHEEL
xmldt-0.0.13.dist-info/METADATA
xmldt-0.0.13.dist-info/RECORD
