Metadata-Version: 2.1
Name: xmldt
Version: 0.0.13
Summary: python module to Down Translate XML
Author-email: Alberto Simões <ambs@zbr.pt>, José João Almeida <jj@di.uminho.pt>
Classifier: License :: OSI Approved :: MIT License
Requires-Dist: lxml
Project-URL: Home, https://natura.di.uminho.pt/svn/main/python/XML-DT/
